aiprogs/__init__.py
aiprogs-0.1.3.dist-info/METADATA
aiprogs-0.1.3.dist-info/WHEEL
aiprogs-0.1.3.dist-info/top_level.txt
aiprogs-0.1.3.dist-info/RECORD
