Metadata-Version: 2.1
Name: aiprogs
Version: 0.1.3
Summary: Lucifer helps you do stuff
Author: Lucifer
Classifier: Programming Language :: Python :: 3
Classifier: License :: OSI Approved :: MIT License
Classifier: Operating System :: OS Independent
Requires-Python: >=3.6
